ukrainealarm/__init__.py
ukrainealarm/client.py
ukrainealarm-0.0.1.dist-info/METADATA
ukrainealarm-0.0.1.dist-info/WHEEL
ukrainealarm-0.0.1.dist-info/top_level.txt
ukrainealarm-0.0.1.dist-info/RECORD
