Metadata-Version: 2.1
Name: ukrainealarm
Version: 0.0.1
Summary: Implements api.ukrainealarm.com API that returns info about Ukraine air raid alarms.
Home-page: https://github.com/PaulAnnekov/ukrainealarm
Author: Pavlo Annekov
Author-email: paul.annekov@gmail.com
License: MIT
Platform: UNKNOWN
Classifier: Programming Language :: Python :: 3
Classifier: License :: OSI Approved :: MIT License
Classifier: Operating System :: OS Independent
Requires-Dist: aiohttp (>=3.8.1)
